[
    {
        "date": [
            {
                "intialYear": "2004",
                "month": "08",
                "day": "26"
            }
        ],
        "event": "International Dog Day",
        "description": "The aim of promoting this day is to raise awareness about adopting these animals who are currently in rescue centers.",
        "task": [
            "Adopt a dog from your local shelter",
            "Donate to animal welfare organizations.",
            "Take your dog out."
        ],
        "frequency": "Annual",
        "reference": "https://nationaltoday.com/national-dog-day/"
    },
    {
        "date": [
            {
                "intialYear": "1889",
                "month": "05",
                "day": "01"
            }
        ],
        "event": "International Workers' Day",
        "description": "Also known as Labour Day, is a celebration of labourers and the working classes that is promoted by the international labour movement.",
        "task": [
            "",
            "",
            ""
        ],
        "frequency": "Annual",
        "reference": "https://en.wikipedia.org/wiki/International_Workers%27_Day"
    },
    {
        "date": [
            {
                "intialYear": "2013",
                "month": "08",
                "day": "10"
            }
        ],
        "event": "World Lion Day",
        "description": "Celebrated to spread awareness about the conservation of lions.",
        "task": [
            "Visit a local zoo.",
            "Research and support wildlife conservation organizations.",
            "Spread awareness through social media posts, organizing events, etc."
        ],
        "frequency": "Annual",
        "reference": "https://nationaltoday.com/world-lion-day/"
    },
    {
        "date": [
            {
                "intialYear": "2009",
                "month": "09",
                "day": "13"
            }
        ],
        "event": "International  Programmers' Day",
        "description": "Celebrated on the 256th day of the year, it honors programmers around the world.",
        "task": [
            "Learn how to say 'hello, world' in a new language.",
            "Show support for programmers by sharing posts on social media.",
            "Participate in gatherings commemorating the day."
        ],
        "frequency": "Annual",
        "reference": "https://www.timeanddate.com/holidays/world/international-programmers-day"
    },
        {
        "date": [
            {
                "intialYear": "1964",
                "month": "11",
                "day": "28"
            }
        ],
        "event": "Red Planet Day",
        "description": "Commemorates the launch of the Mariner 4 spacecraft and is a day to celebrate the planet Mars and learn more about it",
        "task": [
            "Conduct a Red Planet Day party.",
            "Make posters and write cards to friends.",
            "Learn fun facts about mars."
        ],
        "frequency": "Annual",
        "reference": "https://indianexpress.com/article/explained/explained-sci-tech/red-planet-day-the-missions-that-brought-humans-closer-to-mars-8294521/"
    }
]
